moldyutilites/__init__.py
moldyutilites/networkutilities.py
moldyutilites/osutilities.py
moldyutilities-0.0.1.dist-info/METADATA
moldyutilities-0.0.1.dist-info/WHEEL
moldyutilities-0.0.1.dist-info/top_level.txt
moldyutilities-0.0.1.dist-info/RECORD
