Metadata-Version: 2.1
Name: moldyutilities
Version: 0.0.1
Summary: Utilities to assist in coding
Home-page: UNKNOWN
Author: Eric Nuno
Author-email: ericnuno@gmail.com
License: UNKNOWN
Keywords: python,first package
Platform: UNKNOWN
Classifier: Development Status :: 3 - Alpha
Classifier: Intended Audience :: Education
Classifier: Programming Language :: Python :: 2
Classifier: Programming Language :: Python :: 3
Classifier: Operating System :: MacOS :: MacOS X
Classifier: Operating System :: Microsoft :: Windows
